simple_git_changelog/__init__.py
simple_git_changelog/__main__.py
simple_git_changelog/main.py
simple_git_changelog-1.1.4.dist-info/licenses/LICENSE
simple_git_changelog-1.1.4.dist-info/METADATA
simple_git_changelog-1.1.4.dist-info/WHEEL
simple_git_changelog-1.1.4.dist-info/entry_points.txt
simple_git_changelog-1.1.4.dist-info/top_level.txt
simple_git_changelog-1.1.4.dist-info/RECORD
